setup.py
aurora/__init__.py
aurora/decorators.py
aurora/forms.py
aurora/models.py
aurora/settings.py
aurora/storages.py
aurora/urls.py
aurora/utils.py
aurora/views.py
django_aurora.egg-info/PKG-INFO
django_aurora.egg-info/SOURCES.txt
django_aurora.egg-info/dependency_links.txt
django_aurora.egg-info/top_level.txt