Metadata-Version: 1.0
Name: django-aurora
Version: 0.9.0
Summary: Django decorators and some other utilities.
Home-page: http://aurora.io
Author: Dan Loewenherz
Author-email: dan@aurora.io
License: BSD
Platform: UNKNOWN
